Workbook

Sheet Dashboard
A1: ECOGRID RESORT — Financial Model v1 (June 2026)
A2: All figures unaudited working estimates. Blue = inputs you can change (Assumptions sheet).
A4: Sites connected by 2035 | B4: =Projections!K9 -> 109
A5: Total revenue 2035 (€) | B5: =Projections!K16 -> 42098000
A6: EBITDA 2035 (€) | B6: =Projections!K33 -> 39511820
A7: Recurring share of revenue 2035 | B7: =Projections!K17 -> 0.73597321
A8: First EBITDA-positive year | B8: =INDEX(Projections!B3:K3,MATCH(TRUE(),INDEX(Projections!B33:K33>0,0),0)) -> 2028
A9: Model 2: payback per site (yrs) | B9: ='Site Economics'!B18 -> 11.154599
A10: Model 2: income multiple on CAPEX | B10: ='Site Economics'!B20 -> 1.3447368
A11: Year-1 operating costs (€) | B11: =Projections!B30 -> 872000

Sheet Assumptions
A1: ECOGRID RESORT — Model Assumptions (all € unless stated)
A3: A. PER-SITE ECONOMICS (base = Corsica pilot)
A4: CAPEX, base site (€) | B4: 5700000 | C4: Source: brain.md §6, central scenario, unaudited — 2 MWc PV, 6 MWh LFP, 30-50 EV chargers
A5: Annual client savings, base site (€/yr) | B5: 860000 | C5: Source: brain.md §6, target, unaudited
A6: Average site scale factor (× base) | B6: 1 | C6: Set <1 for smaller clients; scales CAPEX & savings
A7: CAPEX per average site (€) | B7: =B4*B6 -> 5700000
A8: Savings per average site (€/yr) | B8: =B5*B6 -> 860000
A9: EPC margin % (Model 1) | B9: 0.15 | C9: Suggested — to validate with Boris/supplier quotes
A10: SaaS subscription (€/site/yr) | B10: 5000 | C10: Source: Franck, interview 10/06/2026 — updates+support included
A11: Maintenance contract revenue, Model 1 (€/site/yr) | B11: 10000 | C11: Source: Franck — base tier, size-dependent models in progress
A12: Maintenance cost borne by SmartGrid, Model 2 (€/site/yr) | B12: 10000 | C12: Plant owned by SmartGrid (Boris) — assumed = M1 price
A13: Model 2 savings share — SmartGrid | B13: 0.6 | C13: Source: Franck 10/06/2026 — base 50%, plan uses 60% (decision 10/06: higher share lever)
A14: Model 2 contract duration (yrs) | B14: 15 | C14: Decision 10/06/2026: 15-yr contract (was 10-15)
A15: Public aid, % of Model 2 CAPEX | B15: 0.15 | C15: Suggested — ZNI/CRE Corsica lever; validate per site & country (ES/IT generic aids closed 2026)
A16: B. COMPANY RUNNING COSTS
A17: Shareholders paid (count) | B17: 5 | C17: Franck, Mark, Boris, Pierre, Michael — paid from day 1
A18: SH compensation (€/month each) | B18: 5000
A19: Staff (count) | B19: 3 | C19: Joseph + secretary + EU grant specialist (planned hires)
A20: Staff salary (€/month each) | B20: 3000
A21: Office (€/month) | B21: 2000
A22: Software dev + Azure hosting, year 1 (€) | B22: 250000
A23: Software dev + hosting, year 2+ (€/yr) | B23: 150000 | C23: Suggested — to confirm
A24: Marketing (€/month) | B24: 10000
A25: Marketing months in year 1 | B25: 10 | C25: Starts month 3
A26: Travel (€/month) | B26: 5000
A27: Other: insurance, legal, accounting, IP, IT (€/yr) | B27: 30000 | C27: Suggested by Claude — incl. décennale check, trademark filing
A28: Sites per ops technician | B28: 5 | C28: Suggested staffing ratio for O&M scale-up
A29: Ops technician salary (€/month) | B29: 3000
A30: Inflation (%/yr) | B30: 0.02
A31: Land/roof lease term, Model 2 (yrs) | B31: 30 | C31: Per Boris — bail 30 ans, to be contracted
A32: C. DEPLOYMENT RAMP (new sites signed per year — EDIT THESE)
A33: Year | B33: 2026 | C33: 2027 | D33: 2028 | E33: 2029 | F33: 2030 | G33: 2031 | H33: 2032 | I33: 2033 | J33: 2034 | K33: 2035
A34: New Model 1 sites (direct sale) | B34: 0 | C34: 0 | D34: 1 | E34: 2 | F34: 3 | G34: 5 | H34: 7 | I34: 9 | J34: 11 | K34: 13
A35: New Model 2 sites (financed, incl. pilot 2027) | B35: 0 | C35: 1 | D35: 1 | E35: 2 | F35: 4 | G35: 6 | H35: 8 | I35: 10 | J35: 12 | K35: 14
A37: Ramp aligned with brain.md roadmap: pilot 2027, first contracts 2028, industrialisation 2029-31, 100+ sites by 2035.

Sheet Site Economics
A1: Per-site economics (average site = scale factor × Corsica pilot)
A3: MODEL 1 — Direct sale (client pays CAPEX)
A4: Client investment (CAPEX) | B4: =Assumptions!B7 -> 5700000
A5: SmartGrid EPC margin (one-time) | B5: =Assumptions!B7*Assumptions!B9 -> 855000
A6: SaaS revenue (€/yr) | B6: =Assumptions!B10 -> 5000
A7: Maintenance revenue (€/yr) | B7: =Assumptions!B11 -> 10000
A8: Recurring revenue per site (€/yr) | B8: =B6+B7 -> 15000
A9: Client keeps 100% of savings (€/yr) | B9: =Assumptions!B8 -> 860000
A10: Client simple payback (yrs) | B10: =B4/(B9-B6-B7) -> 6.7455621
A12: MODEL 2 — Financed / revenue share (zero client CAPEX)
A13: SmartGrid investment (CAPEX) | B13: =Assumptions!B7 -> 5700000
A14: Savings share to SmartGrid (€/yr) | B14: =Assumptions!B8*Assumptions!B13 -> 516000
A15: SaaS revenue (€/yr) | B15: =Assumptions!B10 -> 5000
A16: Maintenance cost (€/yr) | B16: =-Assumptions!B12 -> -10000
A17: Net annual income to SmartGrid (€/yr) | B17: =B14+B15+B16 -> 511000
A18: Simple payback for SmartGrid (yrs) | B18: =B13/B17 -> 11.154599
A19: Total income over contract (€) | B19: =B17*Assumptions!B14 -> 7665000
A20: Income multiple on CAPEX | B20: =B19/B13 -> 1.3447368
A21: Net CAPEX after public aids | B21: =B13*(1-Assumptions!B15) -> 4845000
A22: Payback on net CAPEX (yrs) | B22: =B21/B17 -> 9.481409
A23: Post-contract tail (yrs, lease − contract) | B23: =Assumptions!B31-Assumptions!B14 -> 15
A24: Tail income (€/yr, assumed = contract net income) | B24: =B17 -> 511000
A25: Lifetime income over 30-yr lease (€) | B25: =B17*Assumptions!B14+B24*B23 -> 15330000
A26: Lifetime multiple on net CAPEX | B26: =B25/B21 -> 3.1640867
A28: Note (10/06/2026): Model 2 structured with 4 levers — 15-yr contract, 60% share, CAPEX net of aids in SPV with green debt, plant retained post-contract until end of 30-yr lease.

Sheet Projections
A1: 10-year projections (€) — full-year revenue convention on cumulative sites
A3: Year | B3: 2026 | C3: 2027 | D3: 2028 | E3: 2029 | F3: 2030 | G3: 2031 | H3: 2032 | I3: 2033 | J3: 2034 | K3: 2035
A4: DEPLOYMENT
A5: New Model 1 sites | B5: =Assumptions!B34 -> 0 | C5: =Assumptions!C34 -> 0 | D5: =Assumptions!D34 -> 1 | E5: =Assumptions!E34 -> 2 | F5: =Assumptions!F34 -> 3 | G5: =Assumptions!G34 -> 5 | H5: =Assumptions!H34 -> 7 | I5: =Assumptions!I34 -> 9 | ... K5: =Assumptions!K34 -> 13
A6: New Model 2 sites | B6: =Assumptions!B35 -> 0 | C6: =Assumptions!C35 -> 1 | D6: =Assumptions!D35 -> 1 | E6: =Assumptions!E35 -> 2 | F6: =Assumptions!F35 -> 4 | G6: =Assumptions!G35 -> 6 | H6: =Assumptions!H35 -> 8 | I6: =Assumptions!I35 -> 10 | ... K6: =Assumptions!K35 -> 14
A7: Cumulative Model 1 sites | B7: =SUM($B$5:B5) -> 0 | C7: =SUM($B$5:C5) -> 0 | D7: =SUM($B$5:D5) -> 1 | E7: =SUM($B$5:E5) -> 3 | F7: =SUM($B$5:F5) -> 6 | G7: =SUM($B$5:G5) -> 11 | H7: =SUM($B$5:H5) -> 18 | I7: =SUM($B$5:I5) -> 27 | ... K7: =SUM($B$5:K5) -> 51
A8: Cumulative Model 2 sites | B8: =SUM($B$6:B6) -> 0 | C8: =SUM($B$6:C6) -> 1 | D8: =SUM($B$6:D6) -> 2 | E8: =SUM($B$6:E6) -> 4 | F8: =SUM($B$6:F6) -> 8 | G8: =SUM($B$6:G6) -> 14 | H8: =SUM($B$6:H6) -> 22 | I8: =SUM($B$6:I6) -> 32 | ... K8: =SUM($B$6:K6) -> 58
A9: Total sites connected | B9: =B7+B8 -> 0 | C9: =C7+C8 -> 1 | D9: =D7+D8 -> 3 | E9: =E7+E8 -> 7 | F9: =F7+F8 -> 14 | G9: =G7+G8 -> 25 | H9: =H7+H8 -> 40 | I9: =I7+I8 -> 59 | ... K9: =K7+K8 -> 109
A11: REVENUE
A12: EPC margin (Model 1, one-time) | B12: =B5*Assumptions!$B$7*Assumptions!$B$9 -> 0 | C12: =C5*Assumptions!$B$7*Assumptions!$B$9 -> 0 | D12: =D5*Assumptions!$B$7*Assumptions!$B$9 -> 855000 | E12: =E5*Assumptions!$B$7*Assumptions!$B$9 -> 1710000 | F12: =F5*Assumptions!$B$7*Assumptions!$B$9 -> 2565000 | G12: =G5*Assumptions!$B$7*Assumptions!$B$9 -> 4275000 | H12: =H5*Assumptions!$B$7*Assumptions!$B$9 -> 5985000 | I12: =I5*Assumptions!$B$7*Assumptions!$B$9 -> 7695000 | ... K12: =K5*Assumptions!$B$7*Assumptions!$B$9 -> 11115000
A13: SaaS subscriptions | B13: =B9*Assumptions!$B$10 -> 0 | C13: =C9*Assumptions!$B$10 -> 5000 | D13: =D9*Assumptions!$B$10 -> 15000 | E13: =E9*Assumptions!$B$10 -> 35000 | F13: =F9*Assumptions!$B$10 -> 70000 | G13: =G9*Assumptions!$B$10 -> 125000 | H13: =H9*Assumptions!$B$10 -> 200000 | I13: =I9*Assumptions!$B$10 -> 295000 | ... K13: =K9*Assumptions!$B$10 -> 545000
A14: Maintenance contracts (Model 1) | B14: =B7*Assumptions!$B$11 -> 0 | C14: =C7*Assumptions!$B$11 -> 0 | D14: =D7*Assumptions!$B$11 -> 10000 | E14: =E7*Assumptions!$B$11 -> 30000 | F14: =F7*Assumptions!$B$11 -> 60000 | G14: =G7*Assumptions!$B$11 -> 110000 | H14: =H7*Assumptions!$B$11 -> 180000 | I14: =I7*Assumptions!$B$11 -> 270000 | ... K14: =K7*Assumptions!$B$11 -> 510000
A15: Savings share (Model 2) | B15: =B8*Assumptions!$B$8*Assumptions!$B$13 -> 0 | C15: =C8*Assumptions!$B$8*Assumptions!$B$13 -> 516000 | D15: =D8*Assumptions!$B$8*Assumptions!$B$13 -> 1032000 | E15: =E8*Assumptions!$B$8*Assumptions!$B$13 -> 2064000 | F15: =F8*Assumptions!$B$8*Assumptions!$B$13 -> 4128000 | G15: =G8*Assumptions!$B$8*Assumptions!$B$13 -> 7224000 | H15: =H8*Assumptions!$B$8*Assumptions!$B$13 -> 11352000 | I15: =I8*Assumptions!$B$8*Assumptions!$B$13 -> 16512000 | ... K15: =K8*Assumptions!$B$8*Assumptions!$B$13 -> 29928000
A16: Total revenue | B16: =SUM(B12:B15) -> 0 | C16: =SUM(C12:C15) -> 521000 | D16: =SUM(D12:D15) -> 1912000 | E16: =SUM(E12:E15) -> 3839000 | F16: =SUM(F12:F15) -> 6823000 | G16: =SUM(G12:G15) -> 11734000 | H16: =SUM(H12:H15) -> 17717000 | I16: =SUM(I12:I15) -> 24772000 | ... K16: =SUM(K12:K15) -> 42098000
A17: of which recurring | B17: =IF(B16=0,0,(B13+B14+B15)/B16) -> 0 | C17: =IF(C16=0,0,(C13+C14+C15)/C16) -> 1 | D17: =IF(D16=0,0,(D13+D14+D15)/D16) -> 0.55282427 | E17: =IF(E16=0,0,(E13+E14+E15)/E16) -> 0.5545715 | F17: =IF(F16=0,0,(F13+F14+F15)/F16) -> 0.62406566 | G17: =IF(G16=0,0,(G13+G14+G15)/G16) -> 0.63567411 | H17: =IF(H16=0,0,(H13+H14+H15)/H16) -> 0.66218886 | I17: =IF(I16=0,0,(I13+I14+I15)/I16) -> 0.68936703 | ... K17: =IF(K16=0,0,(K13+K14+K15)/K16) -> 0.73597321
A19: OPERATING COSTS
A20: Inflation factor | B20: =(1+Assumptions!$B$30)^(COLUMN()-2) -> 1 | C20: =(1+Assumptions!$B$30)^(COLUMN()-2) -> 1.02 | D20: =(1+Assumptions!$B$30)^(COLUMN()-2) -> 1.0404 | E20: =(1+Assumptions!$B$30)^(COLUMN()-2) -> 1.061208 | F20: =(1+Assumptions!$B$30)^(COLUMN()-2) -> 1.0824322 | G20: =(1+Assumptions!$B$30)^(COLUMN()-2) -> 1.1040808 | H20: =(1+Assumptions!$B$30)^(COLUMN()-2) -> 1.1261624 | I20: =(1+Assumptions!$B$30)^(COLUMN()-2) -> 1.1486857 | ... K20: =(1+Assumptions!$B$30)^(COLUMN()-2) -> 1.1950926
A21: Salaries — shareholders (5) | B21: =Assumptions!$B$17*Assumptions!$B$18*12*B20 -> 300000 | C21: =Assumptions!$B$17*Assumptions!$B$18*12*C20 -> 306000 | D21: =Assumptions!$B$17*Assumptions!$B$18*12*D20 -> 312120 | E21: =Assumptions!$B$17*Assumptions!$B$18*12*E20 -> 318362.4 | F21: =Assumptions!$B$17*Assumptions!$B$18*12*F20 -> 324729.65 | G21: =Assumptions!$B$17*Assumptions!$B$18*12*G20 -> 331224.24 | H21: =Assumptions!$B$17*Assumptions!$B$18*12*H20 -> 337848.73 | I21: =Assumptions!$B$17*Assumptions!$B$18*12*I20 -> 344605.7 | ... K21: =Assumptions!$B$17*Assumptions!$B$18*12*K20 -> 358527.77
A22: Salaries — staff | B22: =Assumptions!$B$19*Assumptions!$B$20*12*B20 -> 108000 | C22: =Assumptions!$B$19*Assumptions!$B$20*12*C20 -> 110160 | D22: =Assumptions!$B$19*Assumptions!$B$20*12*D20 -> 112363.2 | E22: =Assumptions!$B$19*Assumptions!$B$20*12*E20 -> 114610.46 | F22: =Assumptions!$B$19*Assumptions!$B$20*12*F20 -> 116902.67 | G22: =Assumptions!$B$19*Assumptions!$B$20*12*G20 -> 119240.73 | H22: =Assumptions!$B$19*Assumptions!$B$20*12*H20 -> 121625.54 | I22: =Assumptions!$B$19*Assumptions!$B$20*12*I20 -> 124058.05 | ... K22: =Assumptions!$B$19*Assumptions!$B$20*12*K20 -> 129070
A23: Salaries — ops technicians | B23: =ROUNDUP(B9/Assumptions!$B$28,0)*Assumptions!$B$29*12*B20 -> 0 | C23: =ROUNDUP(C9/Assumptions!$B$28,0)*Assumptions!$B$29*12*C20 -> 36720 | D23: =ROUNDUP(D9/Assumptions!$B$28,0)*Assumptions!$B$29*12*D20 -> 37454.4 | E23: =ROUNDUP(E9/Assumptions!$B$28,0)*Assumptions!$B$29*12*E20 -> 76406.976 | F23: =ROUNDUP(F9/Assumptions!$B$28,0)*Assumptions!$B$29*12*F20 -> 116902.67 | G23: =ROUNDUP(G9/Assumptions!$B$28,0)*Assumptions!$B$29*12*G20 -> 198734.54 | H23: =ROUNDUP(H9/Assumptions!$B$28,0)*Assumptions!$B$29*12*H20 -> 324334.78 | I23: =ROUNDUP(I9/Assumptions!$B$28,0)*Assumptions!$B$29*12*I20 -> 496232.21 | ... K23: =ROUNDUP(K9/Assumptions!$B$28,0)*Assumptions!$B$29*12*K20 -> 946513.31
A24: Office | B24: =Assumptions!$B$21*12*B20 -> 24000 | C24: =Assumptions!$B$21*12*C20 -> 24480 | D24: =Assumptions!$B$21*12*D20 -> 24969.6 | E24: =Assumptions!$B$21*12*E20 -> 25468.992 | F24: =Assumptions!$B$21*12*F20 -> 25978.372 | G24: =Assumptions!$B$21*12*G20 -> 26497.939 | H24: =Assumptions!$B$21*12*H20 -> 27027.898 | I24: =Assumptions!$B$21*12*I20 -> 27568.456 | ... K24: =Assumptions!$B$21*12*K20 -> 28682.222
A25: Software dev + hosting | B25: =IF(COLUMN()=2,Assumptions!$B$22,Assumptions!$B$23*B20) -> 250000 | C25: =IF(COLUMN()=2,Assumptions!$B$22,Assumptions!$B$23*C20) -> 153000 | D25: =IF(COLUMN()=2,Assumptions!$B$22,Assumptions!$B$23*D20) -> 156060 | E25: =IF(COLUMN()=2,Assumptions!$B$22,Assumptions!$B$23*E20) -> 159181.2 | F25: =IF(COLUMN()=2,Assumptions!$B$22,Assumptions!$B$23*F20) -> 162364.82 | G25: =IF(COLUMN()=2,Assumptions!$B$22,Assumptions!$B$23*G20) -> 165612.12 | H25: =IF(COLUMN()=2,Assumptions!$B$22,Assumptions!$B$23*H20) -> 168924.36 | I25: =IF(COLUMN()=2,Assumptions!$B$22,Assumptions!$B$23*I20) -> 172302.85 | ... K25: =IF(COLUMN()=2,Assumptions!$B$22,Assumptions!$B$23*K20) -> 179263.89
A26: Marketing | B26: =IF(COLUMN()=2,Assumptions!$B$24*Assumptions!$B$25,Assumptions!$B$24*12*B20) -> 100000 | C26: =IF(COLUMN()=2,Assumptions!$B$24*Assumptions!$B$25,Assumptions!$B$24*12*C20) -> 122400 | D26: =IF(COLUMN()=2,Assumptions!$B$24*Assumptions!$B$25,Assumptions!$B$24*12*D20) -> 124848 | E26: =IF(COLUMN()=2,Assumptions!$B$24*Assumptions!$B$25,Assumptions!$B$24*12*E20) -> 127344.96 | F26: =IF(COLUMN()=2,Assumptions!$B$24*Assumptions!$B$25,Assumptions!$B$24*12*F20) -> 129891.86 | G26: =IF(COLUMN()=2,Assumptions!$B$24*Assumptions!$B$25,Assumptions!$B$24*12*G20) -> 132489.7 | H26: =IF(COLUMN()=2,Assumptions!$B$24*Assumptions!$B$25,Assumptions!$B$24*12*H20) -> 135139.49 | I26: =IF(COLUMN()=2,Assumptions!$B$24*Assumptions!$B$25,Assumptions!$B$24*12*I20) -> 137842.28 | ... K26: =IF(COLUMN()=2,Assumptions!$B$24*Assumptions!$B$25,Assumptions!$B$24*12*K20) -> 143411.11
A27: Travel | B27: =Assumptions!$B$26*12*B20 -> 60000 | C27: =Assumptions!$B$26*12*C20 -> 61200 | D27: =Assumptions!$B$26*12*D20 -> 62424 | E27: =Assumptions!$B$26*12*E20 -> 63672.48 | F27: =Assumptions!$B$26*12*F20 -> 64945.93 | G27: =Assumptions!$B$26*12*G20 -> 66244.848 | H27: =Assumptions!$B$26*12*H20 -> 67569.745 | I27: =Assumptions!$B$26*12*I20 -> 68921.14 | ... K27: =Assumptions!$B$26*12*K20 -> 71705.554
A28: Other (insurance, legal, IP, IT) | B28: =Assumptions!$B$27*B20 -> 30000 | C28: =Assumptions!$B$27*C20 -> 30600 | D28: =Assumptions!$B$27*D20 -> 31212 | E28: =Assumptions!$B$27*E20 -> 31836.24 | F28: =Assumptions!$B$27*F20 -> 32472.965 | G28: =Assumptions!$B$27*G20 -> 33122.424 | H28: =Assumptions!$B$27*H20 -> 33784.873 | I28: =Assumptions!$B$27*I20 -> 34460.57 | ... K28: =Assumptions!$B$27*K20 -> 35852.777
A29: Maintenance of Model 2 plants | B29: =B8*Assumptions!$B$12*B20 -> 0 | C29: =C8*Assumptions!$B$12*C20 -> 10200 | D29: =D8*Assumptions!$B$12*D20 -> 20808 | E29: =E8*Assumptions!$B$12*E20 -> 42448.32 | F29: =F8*Assumptions!$B$12*F20 -> 86594.573 | G29: =G8*Assumptions!$B$12*G20 -> 154571.31 | H29: =H8*Assumptions!$B$12*H20 -> 247755.73 | I29: =I8*Assumptions!$B$12*I20 -> 367579.41 | ... K29: =K8*Assumptions!$B$12*K20 -> 693153.69
A30: Total operating costs | B30: =SUM(B21:B29) -> 872000 | C30: =SUM(C21:C29) -> 854760 | D30: =SUM(D21:D29) -> 882259.2 | E30: =SUM(E21:E29) -> 959332.03 | F30: =SUM(F21:F29) -> 1060783.5 | G30: =SUM(G21:G29) -> 1227737.9 | H30: =SUM(H21:H29) -> 1464011.1 | I30: =SUM(I21:I29) -> 1773570.7 | ... K30: =SUM(K21:K29) -> 2586180.3
A32: PROFITABILITY
A33: EBITDA | B33: =B16-B30 -> -872000 | C33: =C16-C30 -> -333760 | D33: =D16-D30 -> 1029740.8 | E33: =E16-E30 -> 2879668 | F33: =F16-F30 -> 5762216.5 | G33: =G16-G30 -> 10506262 | H33: =H16-H30 -> 16252989 | I33: =I16-I30 -> 22998429 | ... K33: =K16-K30 -> 39511820
A34: EBITDA margin | B34: =IF(B16=0,0,B33/B16) -> 0 | C34: =IF(C16=0,0,C33/C16) -> -0.6406142 | D34: =IF(D16=0,0,D33/D16) -> 0.53856736 | E34: =IF(E16=0,0,E33/E16) -> 0.75010887 | F34: =IF(F16=0,0,F33/F16) -> 0.84452828 | G34: =IF(G16=0,0,G33/G16) -> 0.8953692 | H34: =IF(H16=0,0,H33/H16) -> 0.91736687 | I34: =IF(I16=0,0,I33/I16) -> 0.92840422 | ... K34: =IF(K16=0,0,K33/K16) -> 0.93856762
A36: CASH (before financing — Model 2 plants funded via SPVs, see Funding)
A37: Model 2 CAPEX invested (net of aids) | B37: =-B6*Assumptions!$B$7*(1-Assumptions!$B$15) -> 0 | C37: =-C6*Assumptions!$B$7*(1-Assumptions!$B$15) -> -4845000 | D37: =-D6*Assumptions!$B$7*(1-Assumptions!$B$15) -> -4845000 | E37: =-E6*Assumptions!$B$7*(1-Assumptions!$B$15) -> -9690000 | F37: =-F6*Assumptions!$B$7*(1-Assumptions!$B$15) -> -19380000 | G37: =-G6*Assumptions!$B$7*(1-Assumptions!$B$15) -> -29070000 | H37: =-H6*Assumptions!$B$7*(1-Assumptions!$B$15) -> -38760000 | I37: =-I6*Assumptions!$B$7*(1-Assumptions!$B$15) -> -48450000 | ... K37: =-K6*Assumptions!$B$7*(1-Assumptions!$B$15) -> -67830000
A38: Cash flow before financing | B38: =B33+B37 -> -872000 | C38: =C33+C37 -> -5178760 | D38: =D33+D37 -> -3815259.2 | E38: =E33+E37 -> -6810332 | F38: =F33+F37 -> -13617784 | G38: =G33+G37 -> -18563738 | H38: =H33+H37 -> -22507011 | I38: =I33+I37 -> -25451571 | ... K38: =K33+K37 -> -28318180
A39: Cumulative cash flow | B39: =SUM($B$38:B38) -> -872000 | C39: =SUM($B$38:C38) -> -6050760 | D39: =SUM($B$38:D38) -> -9866019.2 | E39: =SUM($B$38:E38) -> -16676351 | F39: =SUM($B$38:F38) -> -30294135 | G39: =SUM($B$38:G38) -> -48857873 | H39: =SUM($B$38:H38) -> -71364884 | I39: =SUM($B$38:I38) -> -96816454 | ... K39: =SUM($B$38:K38) -> -1.5253617e+08

Sheet Funding & Pilot
A1: Pilot funding — Marine de Caprone, Ghisonaccia (Corsica)
A3: Indicative funding mix (€)
A4: Equity | B4: 1400000 | C4: Source: brain.md §6, unaudited central scenario
A5: Senior green debt | B5: 3400000
A6: Public aids / grants | B6: 600000 | C6: See aids status — research note 06/2026: ES NextGen & IT Transizione 5.0 closed; FR prime abolished 06/2026; ZNI Corsica guichet = lever n°1
A7: Leasing | B7: 300000
A8: Total | B8: =SUM(B4:B7) -> 5700000
A9: Check vs CAPEX base site | B9: =B8-Assumptions!B4 -> 0
A11: Scale-up structure (brain.md §5): one asset SPV per site or cluster; three investor profiles (EPC industrial, infrastructure/ombrières, financial). Model 2 plant CAPEX sits in SPVs, not on SmartGrid opco P&L.
A13: Pilot targets (brain.md §6, unaudited)
A14: Annual gains target (€) | B14: 860000
A15: Payback (yrs) | B15: 6-8
A16: CO2 avoided | B16: 70-90%
