Workbook

Sheet Summary
A1: ECOGRID RESORT | SmartGrid Model 2 - Year 1 OPEX
A2: Corsica Pilot XL | Conservative Savings Scenario: 500,000 EUR/yr
A4: Indicator | B4: Value | C4: Notes
A5: Annual savings (client) | B5: 500,000 EUR | C5: Conservative floor XL site
A6: SG Revenue share (60%) | B6: 300,000 EUR/yr | C6: Ref: Assumptions B11
A7: Net CAPEX invested | B7: 4,845,000 EUR | C7: After 15% public aids
A8: Payback period | B8: 16.4 yrs | C8: WARNING: EXCEEDS 15-YR CONTRACT
A9: Contract duration | B9: 15 yrs
A10: 15-yr total income | B10: 4,425,000 EUR | C10: 300k x 15 yrs
A11: 15-yr net result | B11: -420,000 EUR | C11: NOT VIABLE AT XL 500k
A12: Year 1 OPEX (company) | B12: ~1,210,000 EUR | C12: Investment phase
A14: VIABILITY ALERT: At 500k savings/yr, Model 2 XL payback is 16.4 years, exceeding the 15-year contract. Minimum savings for viability at 60% share: ~580,000. Model 2 recommended for M-size sites or when savings >580k can be demonstrated.

Sheet Assumptions
A4: Section A - Site Economics
A5: Site name | B5: Corsica Pilot XL
A6: CAPEX base (EUR) | B6: 5700000
A7: Scale factor | B7: 1
A8: CAPEX this site | B8: =B6*B7 -> 5700000
A9: Annual client savings (EUR) | B9: 500000
A10: SmartGrid revenue share % | B10: 0.6
A11: SG revenue share income/yr | B11: =B9*B10 -> 300000
A12: SaaS fee/yr (EUR) | B12: 5000
A13: Contract duration (yrs) | B13: 15
A14: Public aids % | B14: 0.15
A15: Net CAPEX after aids | B15: =B8*(1-B14) -> 4845000
A17: Section B - Financing
A18: Equity (EUR) | B18: 1400000
A19: Debt (loan) (EUR) | B19: 3400000
A20: Public aids (EUR) | B20: 600000
A21: Leasing (EUR) | B21: 300000
A22: Total financing | B22: =SUM(B18:B21) -> 5700000
A23: Loan rate | B23: 0.045
A24: Loan term (yrs) | B24: 20
A25: Annual principal | B25: =B19/B24 -> 170000
A26: Year 1 interest | B26: =B19*B23 -> 153000
A27: Annual leasing | B27: =B21/5 -> 60000
A29: Section C - Company OPEX
A30: Shareholders (count) | B30: 5
A31: Shareholder comp/mo (EUR) | B31: 5000
A32: Staff (count) | B32: 3
A33: Staff salary/mo (EUR) | B33: 3000
A34: Office/mo (EUR) | B34: 2000
A35: Software licenses/yr (EUR) | B35: 250000
A36: Marketing/mo (EUR) | B36: 10000
A37: Marketing months | B37: 10
A38: Travel/yr (EUR) | B38: 5000
A39: Legal/yr (EUR) | B39: 30000
A40: Maintenance per unit/yr (EUR) | B40: 10000
A41: Sites deployed Yr1 | B41: 1
A42: Inflation rate | B42: 0.02

Sheet CAPEX & Funding
A1: CAPEX & Funding Summary - Corsica Pilot XL
A3: Item | B3: Amount (EUR) | C3: % of CAPEX | D3: Notes
A4: Total CAPEX | B4: =Assumptions!B8 -> 5700000 | C4: =B4/Assumptions!B8 -> 1 | D4: Full system cost
A5: - Equity | B5: =Assumptions!B18 -> 1400000 | C5: =B5/Assumptions!B8 -> 0.24561404 | D5: SmartGrid + partners
A6: - Debt (bank loan) | B6: =Assumptions!B19 -> 3400000 | C6: =B6/Assumptions!B8 -> 0.59649123 | D6: 20yr @ 4.5%
A7: - Public aids / grants | B7: =Assumptions!B20 -> 600000 | C7: =B7/Assumptions!B8 -> 0.10526316 | D7: 15% est.
A8: - Leasing | B8: =Assumptions!B21 -> 300000 | C8: =B8/Assumptions!B8 -> 0.052631579 | D8: 5yr equipment
A9: Net CAPEX (after aids) | B9: =Assumptions!B15 -> 4845000 | C9: =B9/Assumptions!B8 -> 0.85 | D9: Key invested figure

Sheet OPEX Year 1
A1: OPEX Year 1 — ECOGRID Model 2 | Corsica Pilot XL
A3: REVENUE
A4: Revenue share income (EUR) | C4: =Assumptions!B11 -> 300000
A5: SaaS fees (EUR) | C5: =Assumptions!B12 -> 5000
A6: TOTAL REVENUE | C6: =SUM(C4:C5) -> 305000
A8: COSTS
A9: Shareholders (5 x 5,000 x 12) | C9: =Assumptions!B30*Assumptions!B31*12 -> 300000
A10: Staff (3 x 3,000 x 12) | C10: =Assumptions!B32*Assumptions!B33*12 -> 108000
A11: Office (2,000 x 12) | C11: =Assumptions!B34*12 -> 24000
A12: Software licenses | C12: =Assumptions!B35 -> 250000
A13: Marketing (10,000 x 10 months) | C13: =Assumptions!B36*Assumptions!B37 -> 100000
A14: Travel | C14: =Assumptions!B38 -> 5000
A15: Legal | C15: =Assumptions!B39 -> 30000
A16: O&M site (1 site) | C16: =Assumptions!B40*Assumptions!B41 -> 10000
A17: Debt service (principal + interest) | C17: =Assumptions!B25+Assumptions!B26 -> 323000
A18: Leasing | C18: =Assumptions!B27 -> 60000
A19: TOTAL COSTS | C19: =SUM(C9:C18) -> 1210000
A21: NET OPERATING RESULT | C21: =C6-C19 -> -905000 | D21: Year 1 investment phase — expected negative

Sheet Tier Comparison
A1: Tier | B1: Solar kWp | C1: Storage MWh | D1: EV Chargers | E1: CAPEX (EUR) | F1: Client Savings/yr | G1: M1 Client Payback | H1: M2 SG Share (60%) | I1: M2 SG Payback | J1: M2 Viable?
A2: S | B2: 50-80 | C2: 0.15-0.25 | D2: 2-4 | E2: 200k-350k | F2: 12k-30k | G2: >10 yrs | H2: 7,200-18,000/yr | I2: >15 yrs | J2: NOT VIABLE
A3: M | B3: 250-350 | C3: 0.8-1.0 | D3: 6-10 | E3: 900k-1200k | F3: 70k-130k | G3: 8-13 yrs | H3: 42k-78k/yr | I3: 11.5-19 yrs | J3: MARGINAL
A4: L | B4: 700-900 | C4: 2.1-2.7 | D4: 15-25 | E4: 2100k-2700k | F4: 200k (cons.) | G4: 12.5 yrs | H4: 120k/yr | I4: 17.5-22 yrs | J4: M1 PREFERRED
A5: XL | B5: 1800-2200 | C5: 5.5-6.5 | D5: 30-50 | E5: 5200k-6300k | F5: 500k (cons.) | G5: 11.75 yrs | H5: 300k/yr | I5: 16.4 yrs | J5: M1 PREFERRED
