Workbook

Sheet Summary
A1: ECOGRID RESORT™ — MODEL 2 | Year 1 Investment & Cost Summary
A2: Model 2: SmartGrid finances 100% of CAPEX — Client pays zero upfront — 15-yr revenue-share contract
A3: Pilot site: Marine de Caprone, Ghisonaccia, Corsica · Unaudited estimates — June 2026 · Blue = inputs Black = formulas Green = cross-sheet links
A5: KPI | B5: Value (€) | C5: Sheet reference | D5: Comment
A6: TOTAL CAPEX (gross) | B6: ='CAPEX & Funding'!B13 -> 5700000 | C6: CAPEX & Funding B13 | D6: Equipment + installation — indicative split
A7: — Equity | B7: =Assumptions!B18 -> 1400000 | C7: Assumptions B18 | D7: SmartGrid opco + co-investors
A8: — Senior green debt | B8: =Assumptions!B19 -> 3400000 | C8: Assumptions B19 | D8: 20-yr, ~4.5% indicative
A9: — Public aids / grants | B9: =Assumptions!B20 -> 600000 | C9: Assumptions B20 | D9: ZNI/CRE Corsica lever n°1
A10: — Equipment leasing | B10: =Assumptions!B21 -> 300000 | C10: Assumptions B21 | D10: 5-yr term
A11: NET CAPEX after public aids | B11: =Assumptions!B15 -> 4845000 | C11: Assumptions B15 | D11: Gross CAPEX × (1 – 15% aid)
A12: TOTAL OPEX — Year 1 | B12: ='OPEX Year 1'!N20 -> 882046 | C12: OPEX Year 1 N20 | D12: All operating costs incl. O&M — excl. debt service
A13: — Personnel | B13: ='OPEX Year 1'!N7 -> 408000 | C13: OPEX Year 1 N7 | D13: Shareholders + staff
A14: — Infrastructure & Software | B14: ='OPEX Year 1'!N11 -> 274050 | C14: OPEX Year 1 N11 | D14: Office + software dev + cloud
A15: — Go-to-Market | B15: ='OPEX Year 1'!N15 -> 160000 | C15: OPEX Year 1 N15 | D15: Marketing + travel
A16: — G&A | B16: ='OPEX Year 1'!N19 -> 39996 | C16: OPEX Year 1 N19 | D16: Legal, insurance, IP, O&M site
A17: ANNUAL DEBT SERVICE (Yr1) | B17: ='CAPEX & Funding'!B29 -> 383000 | C17: CAPEX & Funding B29 | D17: Principal + interest + leasing (not counted in OPEX)
A18: TOTAL REVENUE — Year 1 | B18: ='OPEX Year 1'!N25 -> 521004 | C18: OPEX Year 1 N25 | D18: Savings share 60% + SaaS — 1 site full year
A19: NET OPERATING RESULT (pre-debt) | B19: ='OPEX Year 1'!N26 -> -361042 | C19: OPEX Year 1 N26 | D19: Revenue – OPEX (proxy for EBITDA)
A20: NET RESULT AFTER DEBT SERVICE | B20: ='OPEX Year 1'!N30 -> -744046 | C20: OPEX Year 1 N30 | D20: Indicates cash gap in Year 1 — expected negative
A22: KEY METRICS — Model 2 Return | B22: Value | C22: Formula logic | D22: Comment
A23: Simple payback on net CAPEX | B23: =IF(OR('OPEX Year 1'!N26<=0,Assumptions!B15=0),"-",Assumptions!B15/'OPEX Year 1'!N26) -> - | C23: Net CAPEX / annual net operating income | D23: Yr1 view only — payback improves as more sites added
A24: Total income over 15-yr contract | B24: ='OPEX Year 1'!N26*Assumptions!B13 -> -5415630 | C24: Net op. income × contract duration | D24: Simplified — excludes inflation & additional sites
A25: Income multiple on net CAPEX | B25: =IF(OR(Assumptions!B15=0,'OPEX Year 1'!N26<=0),"-",'OPEX Year 1'!N26*Assumptions!B13/Assumptions!B15) -> - | C25: 15-yr total / net CAPEX | D25: Target >2× to justify financing risk
A26: OPEX as % of gross CAPEX | B26: =IF(Assumptions!B6=0,"-",'OPEX Year 1'!N20/Assumptions!B6) -> 0.15474491 | C26: OPEX Yr1 / gross CAPEX base | D26: Benchmark: should fall sharply from Yr2 with additional sites
A27: Revenue coverage ratio | B27: =IF('OPEX Year 1'!N20=0,"-",'OPEX Year 1'!N25/'OPEX Year 1'!N20) -> 0.59067668 | C27: Revenue / OPEX | D27: Coverage <1x in Yr1 (1 site) is expected; target >1x from Yr2
A29: WARNING: All figures are unaudited working estimates as of June 2026. CAPEX split is indicative only — to be confirmed by engineering study and supplier quotes. Public aid amounts subject to application outcome. Debt terms indicative. This model is for internal planning only and does not constitute a financial commitment.

Sheet Assumptions
A1: ECOGRID RESORT™ — Model 2 | Assumptions & Inputs
A2: Blue = hardcoded inputs · Black = formulas · All unaudited — June 2026
A3: Parameter | B3: Value | C3: Source / Note
A4: A. SITE & CONTRACT — Model 2 (SmartGrid finances, client pays zero CAPEX)
A5: Site name / reference | B5: Marine de Caprone, Ghisonaccia (Corsica) | C5: Source: brain.md §6
A6: CAPEX — base site (€) | B6: 5700000 | C6: brain.md §6 central scenario — 2 MWc PV, 6 MWh LFP, 30-50 EV chargers — unaudited
A7: Site scale factor (× base) | B7: 1 | C7: 1.0 = full Corsica pilot; adjust <1 for smaller sites
A8: Effective CAPEX this site (€) | B8: =B6*B7 -> 5700000 | C8: Gross CAPEX = base × scale factor
A9: Annual client energy savings (€/yr) | B9: 860000 | C9: Source: brain.md §6 — target, unaudited
A10: SmartGrid savings share (%) | B10: 0.6 | C10: Source: Franck 10/06/2026 — 60% base
A11: SmartGrid gross savings income (€/yr) | B11: =B9*B10 -> 516000 | C11: Annual savings × share %
A12: SaaS subscription (€/site/yr) | B12: 5000 | C12: Source: Franck 10/06/2026
A13: Contract duration (yrs) | B13: 15 | C13: Decision 10/06/2026: 15-yr contract
A14: Public aid / grant (% of CAPEX) | B14: 0.15 | C14: ZNI/CRE Corsica lever — validate per site; ES/IT aids closed 2026
A15: Net CAPEX after public aids (€) | B15: =B8*(1-B14) -> 4845000 | C15: Gross CAPEX × (1 – aid %)
A17: B. FUNDING STRUCTURE — Pilot 5.7 M€
A18: Equity (SmartGrid + co-investors) (€) | B18: 1400000 | C18: Source: brain.md §6, unaudited central scenario
A19: Senior green debt (€) | B19: 3400000 | C19: Source: brain.md §6 — BEI / green bond
A20: Public aids / grants (€) | B20: 600000 | C20: ZNI/CRE Corsica lever n°1 — ES/IT aids closed 2026
A21: Equipment leasing (€) | B21: 300000 | C21: Source: brain.md §6
A22: Total funding (€) | B22: =SUM(B18:B21) -> 5700000
A23: Green debt interest rate (%/yr) | B23: 0.045 | C23: Indicative — confirm with lender
A24: Green debt term (yrs) | B24: 20 | C24: Indicative
A25: Annual debt principal repayment (€/yr) | B25: =B19/B24 -> 170000 | C25: Straight-line; actual schedule to confirm with lender
A26: Annual interest — Year 1 (€/yr) | B26: =B19*B23 -> 153000 | C26: Year 1 interest on full balance
A27: Leasing annual payment (€/yr) | B27: =B21/5 -> 60000 | C27: 5-yr lease term assumed
A29: C. COMPANY OPERATING COSTS — Year 1 Inputs
A30: Shareholders paid (count) | B30: 5 | C30: Franck, Mark, Boris, Pierre, Michael — paid from Day 1
A31: SH monthly compensation (€/person/mo) | B31: 5000 | C31: Source: Franck 10/06/2026
A32: Staff headcount | B32: 3 | C32: Joseph + secretary + EU grant specialist
A33: Staff monthly salary (€/person/mo) | B33: 3000 | C33: Source: Franck 10/06/2026
A34: Office rent & utilities (€/mo) | B34: 2000 | C34: Source: Franck 10/06/2026
A35: Software dev + Azure/cloud hosting Yr1 (€) | B35: 250000 | C35: Source: Franck 10/06/2026
A36: Marketing budget (€/mo) | B36: 10000 | C36: Source: Franck 10/06/2026
A37: Marketing active months in Yr1 | B37: 10 | C37: Starts month 3 (setup in months 1-2)
A38: Travel & site visits (€/mo) | B38: 5000 | C38: Source: Franck 10/06/2026
A39: Insurance, legal, accounting, IP (€/yr) | B39: 30000 | C39: Incl. trademark filing, décennale — suggested by Claude
A40: O&M maintenance per Model 2 site (€/yr) | B40: 10000 | C40: SmartGrid bears O&M in Model 2 — Source: Franck
A41: Model 2 sites live in Yr1 | B41: 1 | C41: Corsica pilot — assumed operational full year (conservative)
A42: Inflation (%/yr, for Yr2+ only) | B42: 0.02 | C42: Applied to projections from Yr2 onward

Sheet CAPEX & Funding
A1: ECOGRID RESORT™ — Model 2 | CAPEX Investment & Funding | Pilot: Marine de Caprone, Corsica
A2: All figures unaudited — June 2026 · Model 2: SmartGrid finances 100% of CAPEX; client pays zero upfront
A3: Item | B3: Gross (€) | C3: Net of Aids (€) | D3: Notes
A4: 1. CAPEX BREAKDOWN — Equipment & Installation (indicative split)
A5: Solar PV system — 2 MWc (panels, inverters, mounting) | B5: 2200000 | C5: =B5 -> 2200000 | D5: ~38% — indicative; to confirm with supplier quotes
A6: Battery storage — LFP 6 MWh (V2G-ready) | B6: 1500000 | C6: =B6 -> 1500000 | D6: ~26% — LFP preferred for cycle life & safety
A7: EV charging stations — 30–50 units (OCPP bidirectional) | B7: 600000 | C7: =B7 -> 600000 | D7: ~11% — V2G chargers
A8: EMS / IoT gateways & sensors | B8: 150000 | C8: =B8 -> 150000 | D8: ~3% — FoxESS multi-vendor API hardware
A9: MV/LV grid connection & electrical BOS | B9: 500000 | C9: =B9 -> 500000 | D9: ~9% — metering, distribution
A10: Civil works & mounting structures (ombrières) | B10: 350000 | C10: =B10 -> 350000 | D10: ~6% — foundations, trenching
A11: Engineering, procurement & commissioning (EPC) | B11: 250000 | C11: =B11 -> 250000 | D11: ~4%
A12: Project management, permitting & contingency | B12: 150000 | C12: =B12 -> 150000 | D12: ~3%
A13: TOTAL CAPEX | B13: =SUM(B5:B12) -> 5700000 | C13: =B13*(1-Assumptions!B14) -> 4845000 | D13: Net = Gross × (1 – 15% public aid from Assumptions B14)
A14: brain.md §6 reference (5.7 M€ central scenario) | B14: =Assumptions!B6 -> 5700000 | C14: =Assumptions!B15 -> 4845000 | D14: from Assumptions sheet
A16: 2. FUNDING STRUCTURE — How the CAPEX is financed
A17: Source | B17: Amount (€) | C17: % of Total | D17: Notes
A18: Equity (SmartGrid opco + co-investors) | B18: =Assumptions!B18 -> 1400000 | C18: =B18/B22 -> 0.24561404 | D18: Source: brain.md §6
A19: Senior green debt (BEI / green bond) | B19: =Assumptions!B19 -> 3400000 | C19: =B19/B22 -> 0.59649123 | D19: 20-yr term, ~4.5% indicative — to confirm
A20: Public aids / grants (ZNI CRE Corsica) | B20: =Assumptions!B20 -> 600000 | C20: =B20/B22 -> 0.10526316 | D20: ZNI Corsica lever n°1 — ES/IT aids closed 2026
A21: Equipment leasing | B21: =Assumptions!B21 -> 300000 | C21: =B21/B22 -> 0.052631579 | D21: 5-yr leasing on specific equipment
A22: TOTAL FUNDING | B22: =SUM(B18:B21) -> 5700000 | C22: 100.0%
A24: 3. ANNUAL DEBT SERVICE — Year 1 (financial charges, not counted in OPEX)
A25: Component | B25: Annual Amount (€) | D25: Notes
A26: Principal repayment — green debt | B26: =Assumptions!B25 -> 170000 | D26: Straight-line over 20 yrs — indicative
A27: Interest — green debt (Year 1) | B27: =Assumptions!B26 -> 153000 | D27: Year 1 interest on full 3.4 M€ balance
A28: Leasing annual payment | B28: =Assumptions!B27 -> 60000 | D28: 5-yr leasing term
A29: TOTAL ANNUAL DEBT SERVICE (Yr1) | B29: =SUM(B26:B28) -> 383000 | D29: Principal + interest + leasing

Sheet OPEX Year 1
A1: ECOGRID RESORT™ — Model 2 | OPEX Year 1 | Monthly Forecast
A2: Model 2: SmartGrid finances & owns installation under 15-yr revenue-share contract · All € unaudited — June 2026
A3: Cost Category | B3: Jan | C3: Feb | D3: Mar | E3: Apr | F3: May | G3: Jun | H3: Jul | I3: Aug | J3: Sep | K3: Oct | L3: Nov | M3: Dec | N3: TOTAL Yr1 | O3: Source / Notes
A4: PERSONNEL COSTS
A5: Shareholders compensation (5 × 5,000 €/mo) | B5: =Assumptions!$B$30*Assumptions!$B$31 -> 25000 | C5: =Assumptions!$B$30*Assumptions!$B$31 -> 25000 | D5: =Assumptions!$B$30*Assumptions!$B$31 -> 25000 | E5: =Assumptions!$B$30*Assumptions!$B$31 -> 25000 | F5: =Assumptions!$B$30*Assumptions!$B$31 -> 25000 | G5: =Assumptions!$B$30*Assumptions!$B$31 -> 25000 | H5: =Assumptions!$B$30*Assumptions!$B$31 -> 25000 | I5: =Assumptions!$B$30*Assumptions!$B$31 -> 25000 | ... M5: =Assumptions!$B$30*Assumptions!$B$31 -> 25000 | N5: =SUM(B5:M5) -> 300000 | O5: 5 shareholders paid from Day 1 @ 5k€/mo — Source: Franck 10/06/2026
A6: Staff salaries (3 FTE × 3,000 €/mo) | B6: =Assumptions!$B$32*Assumptions!$B$33 -> 9000 | C6: =Assumptions!$B$32*Assumptions!$B$33 -> 9000 | D6: =Assumptions!$B$32*Assumptions!$B$33 -> 9000 | E6: =Assumptions!$B$32*Assumptions!$B$33 -> 9000 | F6: =Assumptions!$B$32*Assumptions!$B$33 -> 9000 | G6: =Assumptions!$B$32*Assumptions!$B$33 -> 9000 | H6: =Assumptions!$B$32*Assumptions!$B$33 -> 9000 | I6: =Assumptions!$B$32*Assumptions!$B$33 -> 9000 | ... M6: =Assumptions!$B$32*Assumptions!$B$33 -> 9000 | N6: =SUM(B6:M6) -> 108000 | O6: Joseph + secretary + EU grant specialist — Source: Franck 10/06/2026
A7: Subtotal | B7: =B5+B6 -> 34000 | C7: =C5+C6 -> 34000 | D7: =D5+D6 -> 34000 | E7: =E5+E6 -> 34000 | F7: =F5+F6 -> 34000 | G7: =G5+G6 -> 34000 | H7: =H5+H6 -> 34000 | I7: =I5+I6 -> 34000 | ... N7: =N5+N6 -> 408000
A8: INFRASTRUCTURE & SOFTWARE
A9: Office rent & utilities (2,000 €/mo) | B9: =Assumptions!$B$34 -> 2000 | C9: =Assumptions!$B$34 -> 2000 | D9: =Assumptions!$B$34 -> 2000 | E9: =Assumptions!$B$34 -> 2000 | F9: =Assumptions!$B$34 -> 2000 | G9: =Assumptions!$B$34 -> 2000 | H9: =Assumptions!$B$34 -> 2000 | I9: =Assumptions!$B$34 -> 2000 | ... M9: =Assumptions!$B$34 -> 2000 | N9: =SUM(B9:M9) -> 24000 | O9: Source: Franck 10/06/2026
A10: Software dev + Azure / cloud hosting (250k€/yr — front-loaded) | B10: =ROUND(Assumptions!$B$35*0.1,0) -> 25000 | C10: =ROUND(Assumptions!$B$35*0.1,0) -> 25000 | D10: =ROUND(Assumptions!$B$35*0.1,0) -> 25000 | E10: =ROUND(Assumptions!$B$35*0.1,0) -> 25000 | F10: =ROUND(Assumptions!$B$35*0.1,0) -> 25000 | G10: =ROUND(Assumptions!$B$35*0.1,0) -> 25000 | H10: =ROUND(Assumptions!$B$35*0.0667,0) -> 16675 | I10: =ROUND(Assumptions!$B$35*0.0667,0) -> 16675 | J10: =ROUND(Assumptions!$B$35*0.0667,0) -> 16675 | K10: =ROUND(Assumptions!$B$35*0.0667,0) -> 16675 | L10: =ROUND(Assumptions!$B$35*0.0667,0) -> 16675 | M10: =ROUND(Assumptions!$B$35*0.0667,0) -> 16675 | N10: =SUM(B10:M10) -> 250050 | O10: 60% in H1 (dev sprint), 40% in H2 (deployment + hosting) — Source: Franck
A11: Subtotal | B11: =B9+B10 -> 27000 | C11: =C9+C10 -> 27000 | D11: =D9+D10 -> 27000 | E11: =E9+E10 -> 27000 | F11: =F9+F10 -> 27000 | G11: =G9+G10 -> 27000 | H11: =H9+H10 -> 18675 | I11: =I9+I10 -> 18675 | ... N11: =N9+N10 -> 274050
A12: GO-TO-MARKET
A13: Marketing & communications (starts Month 3) | B13: 0 | C13: 0 | D13: =Assumptions!$B$36 -> 10000 | E13: =Assumptions!$B$36 -> 10000 | F13: =Assumptions!$B$36 -> 10000 | G13: =Assumptions!$B$36 -> 10000 | H13: =Assumptions!$B$36 -> 10000 | I13: =Assumptions!$B$36 -> 10000 | J13: =Assumptions!$B$36 -> 10000 | K13: =Assumptions!$B$36 -> 10000 | ... M13: =Assumptions!$B$36 -> 10000 | N13: =SUM(B13:M13) -> 100000 | O13: 10k€/mo × 10 months — months 1-2 = setup (0) — Source: Franck
A14: Travel & client visits (5,000 €/mo) | B14: =Assumptions!$B$38 -> 5000 | C14: =Assumptions!$B$38 -> 5000 | D14: =Assumptions!$B$38 -> 5000 | E14: =Assumptions!$B$38 -> 5000 | F14: =Assumptions!$B$38 -> 5000 | G14: =Assumptions!$B$38 -> 5000 | H14: =Assumptions!$B$38 -> 5000 | I14: =Assumptions!$B$38 -> 5000 | ... M14: =Assumptions!$B$38 -> 5000 | N14: =SUM(B14:M14) -> 60000 | O14: Site visits, investor meetings, EU travel — Source: Franck
A15: Subtotal | B15: =B13+B14 -> 5000 | C15: =C13+C14 -> 5000 | D15: =D13+D14 -> 15000 | E15: =E13+E14 -> 15000 | F15: =F13+F14 -> 15000 | G15: =G13+G14 -> 15000 | H15: =H13+H14 -> 15000 | I15: =I13+I14 -> 15000 | ... N15: =N13+N14 -> 160000
A16: GENERAL & ADMINISTRATIVE
A17: Insurance, legal, accounting, IP, trademark (30k€/yr — quarterly) | B17: 0 | C17: 0 | D17: =ROUND(Assumptions!$B$39/4,0) -> 7500 | E17: 0 | F17: 0 | G17: =ROUND(Assumptions!$B$39/4,0) -> 7500 | H17: 0 | I17: 0 | J17: =ROUND(Assumptions!$B$39/4,0) -> 7500 | K17: 0 | L17: 0 | M17: =ROUND(Assumptions!$B$39/4,0) -> 7500 | N17: =SUM(B17:M17) -> 30000 | O17: Paid quarterly — incl. trademark filing, décennale, legal retainer — suggested
A18: O&M maintenance — Model 2 site(s) (10k€/site/yr) | B18: =ROUND(Assumptions!$B$40*Assumptions!$B$41/12,0) -> 833 | C18: =ROUND(Assumptions!$B$40*Assumptions!$B$41/12,0) -> 833 | D18: =ROUND(Assumptions!$B$40*Assumptions!$B$41/12,0) -> 833 | E18: =ROUND(Assumptions!$B$40*Assumptions!$B$41/12,0) -> 833 | F18: =ROUND(Assumptions!$B$40*Assumptions!$B$41/12,0) -> 833 | G18: =ROUND(Assumptions!$B$40*Assumptions!$B$41/12,0) -> 833 | H18: =ROUND(Assumptions!$B$40*Assumptions!$B$41/12,0) -> 833 | I18: =ROUND(Assumptions!$B$40*Assumptions!$B$41/12,0) -> 833 | ... M18: =ROUND(Assumptions!$B$40*Assumptions!$B$41/12,0) -> 833 | N18: =SUM(B18:M18) -> 9996 | O18: SmartGrid bears O&M in Model 2 — 10k€/site/yr — Source: Franck
A19: Subtotal | B19: =B17+B18 -> 833 | C19: =C17+C18 -> 833 | D19: =D17+D18 -> 8333 | E19: =E17+E18 -> 833 | F19: =F17+F18 -> 833 | G19: =G17+G18 -> 8333 | H19: =H17+H18 -> 833 | I19: =I17+I18 -> 833 | ... N19: =N17+N18 -> 39996
A20: TOTAL OPEX (excl. debt service) | B20: =B5+B6+B9+B10+B13+B14+B17+B18 -> 66833 | C20: =C5+C6+C9+C10+C13+C14+C17+C18 -> 66833 | D20: =D5+D6+D9+D10+D13+D14+D17+D18 -> 84333 | E20: =E5+E6+E9+E10+E13+E14+E17+E18 -> 76833 | F20: =F5+F6+F9+F10+F13+F14+F17+F18 -> 76833 | G20: =G5+G6+G9+G10+G13+G14+G17+G18 -> 84333 | H20: =H5+H6+H9+H10+H13+H14+H17+H18 -> 68508 | I20: =I5+I6+I9+I10+I13+I14+I17+I18 -> 68508 | ... N20: =N5+N6+N9+N10+N13+N14+N17+N18 -> 882046
A22: REVENUE — MODEL 2 (assumed full year — 1 site live from Month 1)
A23: Energy savings share — 60% × 860k€ client savings | B23: =ROUND(Assumptions!$B$11/12,0) -> 43000 | C23: =ROUND(Assumptions!$B$11/12,0) -> 43000 | D23: =ROUND(Assumptions!$B$11/12,0) -> 43000 | E23: =ROUND(Assumptions!$B$11/12,0) -> 43000 | F23: =ROUND(Assumptions!$B$11/12,0) -> 43000 | G23: =ROUND(Assumptions!$B$11/12,0) -> 43000 | H23: =ROUND(Assumptions!$B$11/12,0) -> 43000 | I23: =ROUND(Assumptions!$B$11/12,0) -> 43000 | ... M23: =ROUND(Assumptions!$B$11/12,0) -> 43000 | N23: =SUM(B23:M23) -> 516000 | O23: Annual: 860k × 60% = 516k / 12 = 43k/mo — Source: Franck
A24: SaaS subscription (5,000 €/yr / 12) | B24: =ROUND(Assumptions!$B$12/12,0) -> 417 | C24: =ROUND(Assumptions!$B$12/12,0) -> 417 | D24: =ROUND(Assumptions!$B$12/12,0) -> 417 | E24: =ROUND(Assumptions!$B$12/12,0) -> 417 | F24: =ROUND(Assumptions!$B$12/12,0) -> 417 | G24: =ROUND(Assumptions!$B$12/12,0) -> 417 | H24: =ROUND(Assumptions!$B$12/12,0) -> 417 | I24: =ROUND(Assumptions!$B$12/12,0) -> 417 | ... M24: =ROUND(Assumptions!$B$12/12,0) -> 417 | N24: =SUM(B24:M24) -> 5004 | O24: Source: Franck — updates + support included
A25: TOTAL REVENUE | B25: =B23+B24 -> 43417 | C25: =C23+C24 -> 43417 | D25: =D23+D24 -> 43417 | E25: =E23+E24 -> 43417 | F25: =F23+F24 -> 43417 | G25: =G23+G24 -> 43417 | H25: =H23+H24 -> 43417 | I25: =I23+I24 -> 43417 | ... N25: =N23+N24 -> 521004
A26: NET OPERATING RESULT (Revenue – OPEX) | B26: =B25-B20 -> -23416 | C26: =C25-C20 -> -23416 | D26: =D25-D20 -> -40916 | E26: =E25-E20 -> -33416 | F26: =F25-F20 -> -33416 | G26: =G25-G20 -> -40916 | H26: =H25-H20 -> -25091 | I26: =I25-I20 -> -25091 | ... N26: =N25-N20 -> -361042
A28: DEBT SERVICE — Year 1 (financial charges — NOT included in OPEX above)
A29: Annual debt service / 12 (principal + interest + leasing) | B29: =ROUND(('CAPEX & Funding'!B29)/12,0) -> 31917 | C29: =ROUND(('CAPEX & Funding'!B29)/12,0) -> 31917 | D29: =ROUND(('CAPEX & Funding'!B29)/12,0) -> 31917 | E29: =ROUND(('CAPEX & Funding'!B29)/12,0) -> 31917 | F29: =ROUND(('CAPEX & Funding'!B29)/12,0) -> 31917 | G29: =ROUND(('CAPEX & Funding'!B29)/12,0) -> 31917 | H29: =ROUND(('CAPEX & Funding'!B29)/12,0) -> 31917 | I29: =ROUND(('CAPEX & Funding'!B29)/12,0) -> 31917 | J29: =ROUND(('CAPEX & Funding'!B29)/12,0) -> 31917 | K29: =ROUND(('CAPEX & Funding'!B29)/12,0) -> 31917 | L29: =ROUND(('CAPEX & Funding'!B29)/12,0) -> 31917 | M29: =ROUND(('CAPEX & Funding'!B29)/12,0) -> 31917 | N29: =SUM(B29:M29) -> 383004 | O29: Total from CAPEX & Funding sheet / 12 — see that sheet for detail
A30: NET RESULT AFTER DEBT SERVICE | B30: =B26-B29 -> -55333 | C30: =C26-C29 -> -55333 | D30: =D26-D29 -> -72833 | E30: =E26-E29 -> -65333 | F30: =F26-F29 -> -65333 | G30: =G26-G29 -> -72833 | H30: =H26-H29 -> -57008 | I30: =I26-I29 -> -57008 | ... N30: =N26-N29 -> -744046
