Workbook

Sheet Summary
A1: ECOGRID RESORT™ — MODEL 1 | Breakeven Summary
A2: Model 1: Client pays 100% of CAPEX — SmartGrid earns EPC margin (one-time) + SaaS + Maintenance (recurring)
A3: Pilot site: Marine de Caprone, Corsica · Unaudited estimates — June 2026 · Edit 'New sites SIGNED' row in Breakeven sheet to model scenarios
A5: KPI | B5: Value | C5: Reference | D5: Comment
A6: PER-SITE ECONOMICS
A7: EPC margin per site (€ — one-time) | B7: =Assumptions!B8 -> 855000 | C7: Assumptions B8 | D7: 15% × 5.7M€ CAPEX — one lump-sum paid at project completion
A8: SaaS + Maintenance recurring (€/site/yr) | B8: =Assumptions!B11 -> 15000 | C8: Assumptions B11 | D8: 5k€ SaaS + 10k€ maintenance = 15k€/yr per site
A9: Client simple payback (yrs) | B9: =Assumptions!B13 -> 6.7455621 | C9: Assumptions B13 | D9: Client CAPEX / (savings – recurring fees) — improves client ROI story
A11: YEAR 1 COMPANY COSTS
A12: Total OPEX — Year 1 (€) | B12: =Breakeven!Z20/2 -> 819527 | C12: Breakeven Z20 ÷ 2 | D12: Half of 24-month total — no maintenance cost borne by SmartGrid in Model 1
A14: BREAKEVEN ANALYSIS
A15: Breakeven month (from model in Breakeven sheet) | B15: =Breakeven!B24 -> 6 | C15: Breakeven B24 | D15: Based on current ramp scenario — edit 'New sites SIGNED' row to change
A16: Total revenue over 24 months | B16: =Breakeven!Z11 -> 7800000 | C16: Breakeven Z11 | D16: EPC margins + SaaS + maintenance from signed sites
A17: Total OPEX over 24 months | B17: =Breakeven!Z20 -> 1639054 | C17: Breakeven Z20
A18: Cumulative position at Month 24 | B18: =Breakeven!Z22 -> 6160946 | C18: Breakeven Z22 | D18: Positive = profitable over 2 years; negative = still burning cash
A20: SITES REQUIRED TO BREAK EVEN
A21: Sites needed (EPC margin alone covers Yr1 OPEX) | B21: =Breakeven!B29 -> 1 | C21: Breakeven B29 | D21: CEILING(Yr1 OPEX / EPC margin per site, 1)
A22: EPC margin from 1 site vs. annual OPEX | B22: =Assumptions!B8/Breakeven!Z20*2 -> 1.0432847 | C22: Assumptions B8 / (Breakeven Z20÷2) | D22: % of Yr1 OPEX covered by ONE site's EPC margin
A24: WARNING: All figures are unaudited working estimates — June 2026. EPC margin % and site CAPEX to validate with engineering study and supplier quotes. Breakeven timing depends entirely on the sales ramp — edit the 'New sites SIGNED' row in the Breakeven sheet to model optimistic / conservative scenarios.
A26: HOW TO USE THIS MODEL
A27: 1. Go to the Breakeven sheet
A28: 2. Edit Row 5 'New sites SIGNED this month' — enter the number of deals you expect to close each month
A29: 3. Row 22 'Cumulative cash position' updates automatically — watch for when it turns positive
A30: 4. Row 23 marks the exact breakeven month with a checkmark
A31: 5. Adjust EPC margin %, CAPEX, SaaS price etc. in the Assumptions sheet — everything recalculates

Sheet Assumptions
A1: ECOGRID RESORT™ — Model 1 | Assumptions & Inputs
A2: Blue = hardcoded inputs · Black = formulas · All unaudited — June 2026
A3: Parameter | B3: Value | C3: Source / Note
A4: A. PER-SITE REVENUE — Model 1 (client pays CAPEX; SmartGrid earns margin + recurring)
A5: CAPEX per site — base (€) | B5: 5700000 | C5: brain.md §6 central scenario — 2 MWc PV, 6 MWh LFP, 30-50 EV chargers
A6: Site scale factor (× base) | B6: 1 | C6: 1.0 = full Corsica pilot; adjust for smaller sites
A7: EPC margin % (SmartGrid) | B7: 0.15 | C7: Source: brain.md §6 — suggested, to validate with supplier quotes
A8: EPC margin per site (€ — one-time) | B8: =B5*B6*B7 -> 855000 | C8: CAPEX × scale × margin %
A9: SaaS subscription (€/site/yr) | B9: 5000 | C9: Source: Franck 10/06/2026
A10: Maintenance contract revenue (€/site/yr) | B10: 10000 | C10: Source: Franck — base tier, size-dependent models in progress
A11: Total recurring revenue per site (€/yr) | B11: =B9+B10 -> 15000 | C11: SaaS + maintenance
A12: Client annual energy savings (€/yr — for reference) | B12: 860000 | C12: brain.md §6 — client keeps 100% of savings in Model 1
A13: Client simple payback (yrs — indicative) | B13: =IF(B12-B11<=0,"-",B5*B6/(B12-B11)) -> 6.7455621 | C13: Client CAPEX / (savings – SaaS – maintenance) — indicative
A15: B. SALES RAMP — New Sites Signed per Month (Model 1)
A16: Adjust the 'Sites signed' row in the Breakeven sheet directly — or set a monthly default here:
A17: Default new sites signed per month | B17: 0 | C17: Override directly in 'Breakeven' sheet row 5 for each month
A18: Months from signing to EPC payment (lag) | B18: 2 | C18: Indicative — EPC margin paid at project completion
A21: C. COMPANY OPERATING COSTS — Year 1 Inputs (same as Model 2)
A22: Shareholders paid (count) | B22: 5 | C22: Franck, Mark, Boris, Pierre, Michael
A23: SH monthly compensation (€/person/mo) | B23: 5000 | C23: Source: Franck 10/06/2026
A24: Staff headcount | B24: 3 | C24: Joseph + secretary + EU grant specialist
A25: Staff monthly salary (€/person/mo) | B25: 3000 | C25: Source: Franck 10/06/2026
A26: Office rent & utilities (€/mo) | B26: 2000 | C26: Source: Franck 10/06/2026
A27: Software dev + Azure Yr1 (€) | B27: 250000 | C27: Source: Franck 10/06/2026
A28: Marketing (€/mo) | B28: 10000 | C28: Source: Franck 10/06/2026
A29: Marketing active months Yr1 | B29: 10 | C29: Starts month 3
A30: Travel & site visits (€/mo) | B30: 5000 | C30: Source: Franck 10/06/2026
A31: Insurance, legal, accounting, IP (€/yr) | B31: 30000 | C31: Incl. trademark filing, décennale
A32: Inflation (%/yr — Yr2+ only) | B32: 0.02 | C32: Applied from Yr2 onward

Sheet Breakeven
A1: ECOGRID RESORT™ — Model 1 | 24-Month Breakeven Analysis
A2: Model 1: Client pays 100% of CAPEX upfront — SmartGrid earns EPC margin (one-time) + SaaS + Maintenance (recurring) · Unaudited — June 2026
B3: Jan Yr1 | C3: Feb Yr1 | D3: Mar Yr1 | E3: Apr Yr1 | F3: May Yr1 | G3: Jun Yr1 | H3: Jul Yr1 | I3: Aug Yr1 | J3: Sep Yr1 | K3: Oct Yr1 | L3: Nov Yr1 | M3: Dec Yr1 | N3: Jan Yr2 | O3: Feb Yr2 | P3: Mar Yr2 | Q3: Apr Yr2 | R3: May Yr2 | S3: Jun Yr2 | T3: Jul Yr2 | U3: Aug Yr2 | V3: Sep Yr2 | W3: Oct Yr2 | X3: Nov Yr2 | Y3: Dec Yr2 | Z3: TOTAL 24M | AA3: Notes
A4: SITE SALES — adjust 'Sites signed' per month to model different scenarios
A5: New sites SIGNED this month | B5: 0 | C5: 0 | D5: 0 | E5: 1 | F5: 0 | G5: 0 | H5: 0 | I5: 1 | J5: 0 | K5: 0 | L5: 0 | M5: 1 | N5: 0 | O5: 2 | P5: 0 | Q5: 0 | R5: 0 | S5: 2 | T5: 0 | U5: 0 | V5: 0 | W5: 2 | X5: 0 | Y5: 0 | Z5: =SUM(B5:Y5) -> 9 | AA5: EDIT THESE — each number = new site deal signed that month
A6: Cumulative sites (end of month) | B6: =B5 -> 0 | C6: =B6+C5 -> 0 | D6: =C6+D5 -> 0 | E6: =D6+E5 -> 1 | F6: =E6+F5 -> 1 | G6: =F6+G5 -> 1 | H6: =G6+H5 -> 1 | I6: =H6+I5 -> 2 | J6: =I6+J5 -> 2 | ... Y6: =X6+Y5 -> 9 | AA6: Running total of signed sites (SaaS + maintenance start month after signing)
A7: REVENUE — MODEL 1
A8: EPC margin — one-time (€/site signed, with install lag) | B8: =0 -> 0 | C8: =0 -> 0 | D8: =B5*Assumptions!$B$8 -> 0 | E8: =C5*Assumptions!$B$8 -> 0 | F8: =D5*Assumptions!$B$8 -> 0 | G8: =E5*Assumptions!$B$8 -> 855000 | H8: =F5*Assumptions!$B$8 -> 0 | I8: =G5*Assumptions!$B$8 -> 0 | J8: =H5*Assumptions!$B$8 -> 0 | K8: =I5*Assumptions!$B$8 -> 855000 | ... Y8: =W5*Assumptions!$B$8 -> 1710000 | Z8: =SUM(B8:Y8) -> 7695000 | AA8: EPC margin per site × sites signed 2 months earlier (installation lag) — 15% × 5.7M€ = 855k€/site
A9: SaaS subscription revenue (€/mo from live sites) | B9: =0 -> 0 | C9: =B6*Assumptions!$B$9/12 -> 0 | D9: =C6*Assumptions!$B$9/12 -> 0 | E9: =D6*Assumptions!$B$9/12 -> 0 | F9: =E6*Assumptions!$B$9/12 -> 416.66667 | G9: =F6*Assumptions!$B$9/12 -> 416.66667 | H9: =G6*Assumptions!$B$9/12 -> 416.66667 | I9: =H6*Assumptions!$B$9/12 -> 416.66667 | J9: =I6*Assumptions!$B$9/12 -> 833.33333 | ... Y9: =X6*Assumptions!$B$9/12 -> 3750 | Z9: =SUM(B9:Y9) -> 35000 | AA9: SaaS 5k€/site/yr ÷ 12 × cumulative sites from prior month
A10: Maintenance contract revenue (€/mo from live sites) | B10: =0 -> 0 | C10: =B6*Assumptions!$B$10/12 -> 0 | D10: =C6*Assumptions!$B$10/12 -> 0 | E10: =D6*Assumptions!$B$10/12 -> 0 | F10: =E6*Assumptions!$B$10/12 -> 833.33333 | G10: =F6*Assumptions!$B$10/12 -> 833.33333 | H10: =G6*Assumptions!$B$10/12 -> 833.33333 | I10: =H6*Assumptions!$B$10/12 -> 833.33333 | J10: =I6*Assumptions!$B$10/12 -> 1666.6667 | ... Y10: =X6*Assumptions!$B$10/12 -> 7500 | Z10: =SUM(B10:Y10) -> 70000 | AA10: Maintenance 10k€/site/yr ÷ 12 × cumulative sites from prior month
A11: TOTAL REVENUE | B11: =B8+B9+B10 -> 0 | C11: =C8+C9+C10 -> 0 | D11: =D8+D9+D10 -> 0 | E11: =E8+E9+E10 -> 0 | F11: =F8+F9+F10 -> 1250 | G11: =G8+G9+G10 -> 856250 | H11: =H8+H9+H10 -> 1250 | I11: =I8+I9+I10 -> 1250 | ... Z11: =Z8+Z9+Z10 -> 7800000 | AA11: EPC margin + SaaS + Maintenance
A12: COMPANY OPEX (same structure as Model 2)
A13: Shareholders (5 × 5,000 €/mo) | B13: =Assumptions!$B$22*Assumptions!$B$23 -> 25000 | C13: =Assumptions!$B$22*Assumptions!$B$23 -> 25000 | D13: =Assumptions!$B$22*Assumptions!$B$23 -> 25000 | E13: =Assumptions!$B$22*Assumptions!$B$23 -> 25000 | F13: =Assumptions!$B$22*Assumptions!$B$23 -> 25000 | G13: =Assumptions!$B$22*Assumptions!$B$23 -> 25000 | H13: =Assumptions!$B$22*Assumptions!$B$23 -> 25000 | I13: =Assumptions!$B$22*Assumptions!$B$23 -> 25000 | ... Y13: =Assumptions!$B$22*Assumptions!$B$23 -> 25000 | Z13: =SUM(B13:Y13) -> 600000 | AA13: Source: Franck 10/06/2026
A14: Staff salaries (3 FTE × 3,000 €/mo) | B14: =Assumptions!$B$24*Assumptions!$B$25 -> 9000 | C14: =Assumptions!$B$24*Assumptions!$B$25 -> 9000 | D14: =Assumptions!$B$24*Assumptions!$B$25 -> 9000 | E14: =Assumptions!$B$24*Assumptions!$B$25 -> 9000 | F14: =Assumptions!$B$24*Assumptions!$B$25 -> 9000 | G14: =Assumptions!$B$24*Assumptions!$B$25 -> 9000 | H14: =Assumptions!$B$24*Assumptions!$B$25 -> 9000 | I14: =Assumptions!$B$24*Assumptions!$B$25 -> 9000 | ... Y14: =Assumptions!$B$24*Assumptions!$B$25 -> 9000 | Z14: =SUM(B14:Y14) -> 216000 | AA14: Source: Franck 10/06/2026
A15: Office rent & utilities (2,000 €/mo) | B15: =Assumptions!$B$26 -> 2000 | C15: =Assumptions!$B$26 -> 2000 | D15: =Assumptions!$B$26 -> 2000 | E15: =Assumptions!$B$26 -> 2000 | F15: =Assumptions!$B$26 -> 2000 | G15: =Assumptions!$B$26 -> 2000 | H15: =Assumptions!$B$26 -> 2000 | I15: =Assumptions!$B$26 -> 2000 | ... Y15: =Assumptions!$B$26 -> 2000 | Z15: =SUM(B15:Y15) -> 48000 | AA15: Source: Franck
A16: Software dev + Azure / cloud hosting | B16: =ROUND(Assumptions!$B$27*0.1,0) -> 25000 | C16: =ROUND(Assumptions!$B$27*0.1,0) -> 25000 | D16: =ROUND(Assumptions!$B$27*0.1,0) -> 25000 | E16: =ROUND(Assumptions!$B$27*0.1,0) -> 25000 | F16: =ROUND(Assumptions!$B$27*0.1,0) -> 25000 | G16: =ROUND(Assumptions!$B$27*0.1,0) -> 25000 | H16: =ROUND(Assumptions!$B$27*0.0667,0) -> 16675 | I16: =ROUND(Assumptions!$B$27*0.0667,0) -> 16675 | J16: =ROUND(Assumptions!$B$27*0.0667,0) -> 16675 | K16: =ROUND(Assumptions!$B$27*0.0667,0) -> 16675 | L16: =ROUND(Assumptions!$B$27*0.0667,0) -> 16675 | M16: =ROUND(Assumptions!$B$27*0.0667,0) -> 16675 | N16: =ROUND(Assumptions!$B$27*0.5/12,0) -> 10417 | O16: =ROUND(Assumptions!$B$27*0.5/12,0) -> 10417 | P16: =ROUND(Assumptions!$B$27*0.5/12,0) -> 10417 | Q16: =ROUND(Assumptions!$B$27*0.5/12,0) -> 10417 | R16: =ROUND(Assumptions!$B$27*0.5/12,0) -> 10417 | S16: =ROUND(Assumptions!$B$27*0.5/12,0) -> 10417 | T16: =ROUND(Assumptions!$B$27*0.5/12,0) -> 10417 | U16: =ROUND(Assumptions!$B$27*0.5/12,0) -> 10417 | ... Y16: =ROUND(Assumptions!$B$27*0.5/12,0) -> 10417 | Z16: =SUM(B16:Y16) -> 375054 | AA16: Yr1 250k€ (60% H1/40% H2); Yr2 ~125k€ — Source: Franck
A17: Marketing & communications | B17: =0 -> 0 | C17: =0 -> 0 | D17: =Assumptions!$B$28 -> 10000 | E17: =Assumptions!$B$28 -> 10000 | F17: =Assumptions!$B$28 -> 10000 | G17: =Assumptions!$B$28 -> 10000 | H17: =Assumptions!$B$28 -> 10000 | I17: =Assumptions!$B$28 -> 10000 | J17: =Assumptions!$B$28 -> 10000 | K17: =Assumptions!$B$28 -> 10000 | ... Y17: =Assumptions!$B$28 -> 10000 | Z17: =SUM(B17:Y17) -> 220000 | AA17: 10k€/mo from month 3 — Source: Franck
A18: Travel & site visits (5,000 €/mo) | B18: =Assumptions!$B$30 -> 5000 | C18: =Assumptions!$B$30 -> 5000 | D18: =Assumptions!$B$30 -> 5000 | E18: =Assumptions!$B$30 -> 5000 | F18: =Assumptions!$B$30 -> 5000 | G18: =Assumptions!$B$30 -> 5000 | H18: =Assumptions!$B$30 -> 5000 | I18: =Assumptions!$B$30 -> 5000 | ... Y18: =Assumptions!$B$30 -> 5000 | Z18: =SUM(B18:Y18) -> 120000 | AA18: Source: Franck
A19: Insurance, legal, IP, accounting (30k€/yr — quarterly) | B19: =0 -> 0 | C19: =0 -> 0 | D19: =ROUND(Assumptions!$B$31/4,0) -> 7500 | E19: =0 -> 0 | F19: =0 -> 0 | G19: =ROUND(Assumptions!$B$31/4,0) -> 7500 | H19: =0 -> 0 | I19: =0 -> 0 | J19: =ROUND(Assumptions!$B$31/4,0) -> 7500 | K19: =0 -> 0 | L19: =0 -> 0 | M19: =ROUND(Assumptions!$B$31/4,0) -> 7500 | N19: =0 -> 0 | O19: =0 -> 0 | P19: =ROUND(Assumptions!$B$31/4,0) -> 7500 | Q19: =0 -> 0 | R19: =0 -> 0 | S19: =ROUND(Assumptions!$B$31/4,0) -> 7500 | T19: =0 -> 0 | U19: =0 -> 0 | V19: =ROUND(Assumptions!$B$31/4,0) -> 7500 | W19: =0 -> 0 | X19: =0 -> 0 | Y19: =ROUND(Assumptions!$B$31/4,0) -> 7500 | Z19: =SUM(B19:Y19) -> 60000 | AA19: Paid quarterly — incl. trademark, décennale
A20: TOTAL OPEX | B20: =B13+B14+B15+B16+B17+B18+B19 -> 66000 | C20: =C13+C14+C15+C16+C17+C18+C19 -> 66000 | D20: =D13+D14+D15+D16+D17+D18+D19 -> 83500 | E20: =E13+E14+E15+E16+E17+E18+E19 -> 76000 | F20: =F13+F14+F15+F16+F17+F18+F19 -> 76000 | G20: =G13+G14+G15+G16+G17+G18+G19 -> 83500 | H20: =H13+H14+H15+H16+H17+H18+H19 -> 67675 | I20: =I13+I14+I15+I16+I17+I18+I19 -> 67675 | ... Z20: =Z13+Z14+Z15+Z16+Z17+Z18+Z19 -> 1639054 | AA20: Note: Model 1 has NO maintenance cost (client pays separately)
A21: NET RESULT (Revenue – OPEX) | B21: =B11-B20 -> -66000 | C21: =C11-C20 -> -66000 | D21: =D11-D20 -> -83500 | E21: =E11-E20 -> -76000 | F21: =F11-F20 -> -74750 | G21: =G11-G20 -> 772750 | H21: =H11-H20 -> -66425 | I21: =I11-I20 -> -66425 | ... Z21: =Z11-Z20 -> 6160946
A22: CUMULATIVE CASH POSITION ← watch for breakeven | B22: =B21 -> -66000 | C22: =B22+C21 -> -132000 | D22: =C22+D21 -> -215500 | E22: =D22+E21 -> -291500 | F22: =E22+F21 -> -366250 | G22: =F22+G21 -> 406500 | H22: =G22+H21 -> 340075 | I22: =H22+I21 -> 273650 | J22: =I22+J21 -> 200975 | ... Y22: =X22+Y21 -> 6160946 | Z22: =Y22 -> 6160946 | AA22: Cumulative net result — negative = cash burn, positive = breakeven passed. Yellow cells turn read/green with conditional formatting (add in Excel if desired).
A23: BREAKEVEN reached? (first month cumulative > 0) | B23: =IF(B22>0,"✓ YES","") | C23: =IF(AND(C22>0,B22<=0),"✓ BREAKEVEN","") | D23: =IF(AND(D22>0,C22<=0),"✓ BREAKEVEN","") | E23: =IF(AND(E22>0,D22<=0),"✓ BREAKEVEN","") | F23: =IF(AND(F22>0,E22<=0),"✓ BREAKEVEN","") | G23: =IF(AND(G22>0,F22<=0),"✓ BREAKEVEN","") -> ✓ BREAKEVEN | H23: =IF(AND(H22>0,G22<=0),"✓ BREAKEVEN","") | I23: =IF(AND(I22>0,H22<=0),"✓ BREAKEVEN","") | J23: =IF(AND(J22>0,I22<=0),"✓ BREAKEVEN","") | ... Y23: =IF(AND(Y22>0,X22<=0),"✓ BREAKEVEN","") | Z23: =IF(SUMPRODUCT(--(B22:Y22>0))>0,"Breakeven reached","Not yet reached") -> Breakeven reached | AA23: First month where cumulative cash position turns positive
A24: Breakeven month number (from start) | B24: =IFERROR(MATCH(TRUE(),INDEX(B22:Y22>0,0),0),"Not in 24M") -> 6 | AA24: Month index counting from Month 1. Edit the 'New sites SIGNED' row above to see how different ramp speeds affect breakeven.
A26: KEY INSIGHT — Per-Site Revenue
A27: EPC margin per site (€) | B27: =Assumptions!B8 -> 855000 | AA27: One site = one 855k€ lump sum — nearly covers all of Year 1 OPEX
A28: Year 1 OPEX estimate (€) | B28: =Z20/2 -> 819527 | AA28: Approx (24-month total / 2) — see Summary for exact figure
A29: Sites needed to cover Yr1 OPEX with EPC margin alone | B29: =CEILING(Z20/2/Assumptions!B8,1) -> 1 | AA29: Minimum deal count for EPC margin to fully offset Year 1 OPEX (excl. lag)
